MTBF_G90-1.0.3.dist-info/DESCRIPTION.rst
MTBF_G90-1.0.3.dist-info/METADATA
MTBF_G90-1.0.3.dist-info/RECORD
MTBF_G90-1.0.3.dist-info/WHEEL
MTBF_G90-1.0.3.dist-info/metadata.json
MTBF_G90-1.0.3.dist-info/top_level.txt
mtbf_g90/__init__.py
mtbf_g90/gaia_arguments.py
mtbf_g90/runner.py
mtbf_g90/version.py
mtbf_g90/device/__init__.py
mtbf_g90/device/adb.py
mtbf_g90/device/adb_b2g.py
mtbf_g90/device/adbmanager.py
mtbf_g90/device/errors.py
mtbf_g90/device/version.py
mtbf_g90/logi/__init__.py
mtbf_g90/logi/commandline.py
mtbf_g90/logi/logtypes.py
mtbf_g90/logi/reader.py
mtbf_g90/logi/structuredlog.py
mtbf_g90/logi/unstructuredlog.py
mtbf_g90/logi/formatters/__init__.py
mtbf_g90/logi/formatters/base.py
mtbf_g90/logi/formatters/machformatter.py
mtbf_g90/logi/formatters/process.py
mtbf_g90/logi/formatters/tbplformatter.py
mtbf_g90/logi/formatters/unittest.py
mtbf_g90/logi/formatters/xunit.py
mtbf_g90/logi/formatters/html/__init__.py
mtbf_g90/logi/formatters/html/html.py
mtbf_g90/logi/formatters/html/xmlgen.py
mtbf_g90/logi/handlers/__init__.py
mtbf_g90/logi/handlers/base.py
mtbf_g90/logi/handlers/bufferhandler.py
mtbf_g90/marionette_driver/__init__.py
mtbf_g90/marionette_driver/addons.py
mtbf_g90/marionette_driver/by.py
mtbf_g90/marionette_driver/date_time_value.py
mtbf_g90/marionette_driver/decorators.py
mtbf_g90/marionette_driver/errors.py
mtbf_g90/marionette_driver/expected.py
mtbf_g90/marionette_driver/geckoinstance.py
mtbf_g90/marionette_driver/httpd.py
mtbf_g90/marionette_driver/keys.py
mtbf_g90/marionette_driver/localization.py
mtbf_g90/marionette_driver/marionette.py
mtbf_g90/marionette_driver/timeout.py
mtbf_g90/marionette_driver/transport.py
mtbf_g90/marionette_driver/wait.py
mtbf_g90/mozprocess/__init__.py
mtbf_g90/mozprocess/processhandler.py
mtbf_g90/mozprocess/qijo.py
mtbf_g90/mozprocess/winprocess.py
mtbf_g90/test/__init__.py
mtbf_g90/test/case.py
mtbf_g90/test/results.py
