Metadata-Version: 2.0
Name: MTBF-G90
Version: 1.0.3
Summary: marionette driver to establish connection.
Home-page: UNKNOWN
Author: shayan
Author-email: syedshayan109@gmail.com
License: MIT
Download-URL: https://pypi.org/project/mtbf_g90/
Keywords: mtbf_g90,g90
Platform: UNKNOWN
Requires-Dist: mozrunner (==8.3.0)
Requires-Dist: mozversion (==2.4.0)
Requires-Dist: six (==1.16.0)
Requires-Dist: future (==0.18.3)
Requires-Dist: manifestparser (==2.1.0)
